submitit/__init__.py
submitit/conftest.py
submitit/helpers.py
submitit/py.typed
submitit/test_documentation.py
submitit/test_helpers.py
submitit/test_pickle.py
submitit/auto/__init__.py
submitit/auto/auto.py
submitit/auto/test_auto.py
submitit/core/__init__.py
submitit/core/_submit.py
submitit/core/core.py
submitit/core/job_environment.py
submitit/core/logger.py
submitit/core/plugins.py
submitit/core/submission.py
submitit/core/test_async.py
submitit/core/test_core.py
submitit/core/test_plugins.py
submitit/core/test_utils.py
submitit/core/utils.py
submitit/local/__init__.py
submitit/local/_local.py
submitit/local/debug.py
submitit/local/local.py
submitit/local/test_debug.py
submitit/local/test_local.py
submitit/slurm/__init__.py
submitit/slurm/_sbatch_test_record.txt
submitit/slurm/slurm.py
submitit/slurm/test_slurm.py
submitit-1.5.0.dist-info/LICENSE
submitit-1.5.0.dist-info/WHEEL
submitit-1.5.0.dist-info/METADATA
submitit-1.5.0.dist-info/RECORD
