Metadata-Version: 2.1
Name: submitit
Version: 1.5.0
Summary: "Python 3.8+ toolbox for submitting jobs to Slurm
Author: Facebook AI Research
Requires-Python: >=3.8
Classifier: License :: OSI Approved :: MIT License
Classifier: Topic :: System :: Distributed Computing
Classifier: Development Status :: 5 - Production/Stable
Requires-Dist: cloudpickle>=1.2.1
Requires-Dist: typing_extensions>=3.7.4.2
Requires-Dist: pytest>=7.4.2 ; extra == "dev"
Requires-Dist: pytest-asyncio>=0.15.0 ; extra == "dev"
Requires-Dist: pytest-cov>=4.1.0 ; extra == "dev"
Requires-Dist: coverage[toml]>=5.1 ; extra == "dev"
Requires-Dist: black==23.3.0 ; extra == "dev"
Requires-Dist: isort==5.11.5 ; extra == "dev"
Requires-Dist: pre-commit>=1.15.2 ; extra == "dev"
Requires-Dist: mypy>=1.4.1 ; extra == "dev"
Requires-Dist: types-pkg_resources>=0.1.2 ; extra == "dev"
Requires-Dist: pylint>=3.0.0 ; extra == "dev"
Requires-Dist: flit>=3.5.1 ; extra == "dev"
Project-URL: Source, https://github.com/facebookincubator/submitit
Project-URL: Tracker, https://github.com/facebookincubator/submitit/issues
Provides-Extra: dev
